hp_da_pt19/Communication.py
hp_da_pt19/__init__.py
hp_da_pt19/arucoTracking.py
hp_da_pt19/calibration.py
hp_da_pt19/pidaxischanged.py
hp_da_pt19/rectangle.py
hp_da_pt19/utils.py
hp_da_pt19-0.0.2.dist-info/LICENSE
hp_da_pt19-0.0.2.dist-info/METADATA
hp_da_pt19-0.0.2.dist-info/WHEEL
hp_da_pt19-0.0.2.dist-info/top_level.txt
hp_da_pt19-0.0.2.dist-info/RECORD
