Metadata-Version: 2.1
Name: hp-da-pt19
Version: 0.0.2
Summary: Package contaning python wrapper for supporting pitch,roll,yaw, swarms, and more
Home-page: https://github.com/da-vidi21/HP_DA_PT19
Author: Anonymous
Author-email: vidit21srivastava@gmail.com
License: MIT
Keywords: drone,sdk,python
Platform: UNKNOWN
Classifier: Development Status :: 5 - Production/Stable
Classifier: Intended Audience :: Developers
Classifier: Topic :: Software Development :: Build Tools
Classifier: License :: OSI Approved :: MIT License
Classifier: Programming Language :: Python :: 3.6
Classifier: Programming Language :: Python :: 3.7
Classifier: Programming Language :: Python :: 3.8
Classifier: Programming Language :: Python :: 3.9
Requires-Python: >=3.6
Requires-Dist: av
Requires-Dist: matplotlib (==3.6.2)
Requires-Dist: numpy (==1.23.5)
Requires-Dist: opencv-python
Requires-Dist: opencv-contrib-python (==4.5.5.64)
Requires-Dist: pillow
